hunspell/__init__.py
hunspell/_version.py
hunspell/hunspell.cp36-win_amd64.pyd
hunspell/hunspell.cpp
hunspell/hunspell.pxd
hunspell/hunspell.pyx
hunspell/platform.py
hunspell/thread.hpp
hunspell/thread.pxd
hunspell/dictionaries/a.dic
hunspell/dictionaries/en_AU.aff
hunspell/dictionaries/en_AU.dic
hunspell/dictionaries/en_CA.aff
hunspell/dictionaries/en_CA.dic
hunspell/dictionaries/en_GB.aff
hunspell/dictionaries/en_GB.dic
hunspell/dictionaries/en_NZ.aff
hunspell/dictionaries/en_NZ.dic
hunspell/dictionaries/en_US.aff
hunspell/dictionaries/en_US.dic
hunspell/dictionaries/en_ZA.aff
hunspell/dictionaries/en_ZA.dic
hunspell/dictionaries/test.aff
hunspell/dictionaries/test.dic
cyhunspell-2.0.1.dist-info/LICENSE
cyhunspell-2.0.1.dist-info/METADATA
cyhunspell-2.0.1.dist-info/WHEEL
cyhunspell-2.0.1.dist-info/top_level.txt
cyhunspell-2.0.1.dist-info/RECORD
